indico_vc_dummy/__init__.py
indico_vc_dummy/plugin.py
indico_vc_dummy/static/images/dummy_icon.png
indico_vc_dummy/static/images/dummy_logo.png
indico_vc_dummy/templates/info_box.html
indico_vc_dummy/templates/manage_event_create_room.html
indico_vc_dummy/templates/manage_event_info_box.html
indico_vc_dummy/translations/messages.pot
indico_plugin_vc_dummy-3.3.dist-info/METADATA
indico_plugin_vc_dummy-3.3.dist-info/WHEEL
indico_plugin_vc_dummy-3.3.dist-info/entry_points.txt
indico_plugin_vc_dummy-3.3.dist-info/top_level.txt
indico_plugin_vc_dummy-3.3.dist-info/RECORD
